LICENSE
MANIFEST.in
README.md
setup.py
ybai/__init__.py
ybai/__main__.py
ybai.egg-info/PKG-INFO
ybai.egg-info/SOURCES.txt
ybai.egg-info/dependency_links.txt
ybai.egg-info/entry_points.txt
ybai.egg-info/requires.txt
ybai.egg-info/top_level.txt
ybai/api/__init__.py
ybai/api/bot.py
ybai/api/messages/__init__.py
ybai/api/messages/message.py
ybai/api/messages/message_config.py
ybai/api/messages/registered.py