Metadata-Version: 1.1
Name: ybai
Version: 0.0.4
Summary: 个人测试AI
Home-page: https://github.com/mengzhu716/ybai
Author: Yinbing
Author-email: 380711712@qq.com
License: MIT
Keywords: AI,WeChat,API
Platform: UNKNOWN
Classifier: Development Status :: 4 - Beta
Classifier: License :: OSI Approved :: MIT License
Classifier: Programming Language :: Python :: 3
Classifier: Operating System :: OS Independent
Classifier: Topic :: Communications :: Chat
Classifier: Topic :: Utilities
